console_script.py
pythonl
pythonl.pynl
pythonl-0.1.0.dist-info/LICENSE
pythonl-0.1.0.dist-info/METADATA
pythonl-0.1.0.dist-info/WHEEL
pythonl-0.1.0.dist-info/entry_points.txt
pythonl-0.1.0.dist-info/RECORD
