Metadata-Version: 2.1
Name: pythonl
Version: 0.1.0
Summary: Wat als je alleen maar Nederlandse woorden zou gebruiken voor python sleutel woorden?
Home-page: https://github.com/tintin10q/pythonl
License: GPL-3.0-only
Keywords: Dutch,Nederlands,translation,vertaling,taal,language
Author: Quinten Cabo
Author-email: tintin10q@hotmail.com
Requires-Python: >=3.10,<4.0
Classifier: License :: OSI Approved :: GNU General Public License v3 (GPLv3)
Classifier: Programming Language :: Python :: 3
Classifier: Programming Language :: Python :: 3.10
Classifier: Programming Language :: Python :: 3.11
Classifier: Programming Language :: Python :: 3.12
Requires-Dist: token-utils (>=0.1.8,<0.2.0)
Project-URL: Repository, https://github.com/tintin10q/pythonl
